{"run_number": "1744756779760802", "step_name": "analyze_creatures", "task_id": "2", "attempt_id": 0, "name": "_foreach_stack", "content_type": "gzip+pickle-v4", "type": "metaflow.artifact", "sha": "7dcab8ade1907cc4e9407cf64b7ee093fe92df4f", "ds_type": "local", "location": ":root:/Users/adazhang/USF/spring2/ST_msds603/labs/lab6/.metaflow", "flow_id": "ForeachFlow", "user_name": "adazhang", "tags": [], "system_tags": ["metaflow_version:2.15.7", "user:adazhang", "runtime:dev", "python_version:3.12.9"], "ts_epoch": 1744756780007}